{"id":1,"title":"Современные технологии монтажа фундаментов и бурения ям под заборы","excerpt":"Подробный разбор методов монтажа фундаментов на сваях и нюансов бурения ям для столбов заборов с акцентом на современные ямобуры, особенности грунтов и реальные решения для разных условий.","image":"https://bur-expert.ru/images/articles/fundament-bureniya-yamobur-400x300.jpg","date":"2025-05-29","readTime":"7 мин","slug":"sovremennye-tehnologii-montazha-fundamentov-i-bureniya-yam-pod-zabory","meta":{"title":"Технологии монтажа фундаментов и бурения ям под заборы | БурЭксперт","description":"Узнайте о современных методах монтажа фундаментов и эффективных технологиях бурения ям под заборы с использованием ямобуров и спецтехники. Практические советы и решения для любых грунтов."},"html":"<h1>Современные технологии монтажа фундаментов и бурения ям под заборы</h1>\n\n<h2>Введение</h2>\n<p>Монтаж фундаментов и правильная подготовка ям под столбы — это фундаментальные этапы в строительстве и обустройстве любых объектов, будь то жилой дом, дачный участок или территория промышленного назначения. Как показывает практика, качество этих работ во многом определяет надёжность и долговечность всей конструкции. Сегодня современные технологии бурения, в том числе применение ямобуров с телескопическими стрелами и адаптивными манипуляторами, позволяют выполнять эти задачи быстро, точно и с минимальными затратами. В статье мы подробно разберём основные виды фундаментов на сваях, особенности бурения ям под заборы и мелкие конструкции, а также предложим практические решения и примеры из опыта компании БурЭксперт и других профессионалов Челябинска и области.</p>\n<p>Цель этой публикации — дать читателю полный обзор актуальных технологий и оборудования, которые обеспечивают эффективный монтаж фундаментов и аккуратное бурение скважин под столбы. Специальное внимание уделим влиянию типа грунта и условий работ, а также современным техническим инновациям, помогающим оптимизировать процесс и повысить качество результата.</p>\n\n<h2>Монтаж фундаментов на свайных и столбчатых основаниях</h2>\n<p>Фундаменты на сваях являются одним из наиболее надёжных и универсальных решений для возведения конструкций в самых разных условиях. Что важно, выбор типа сваи напрямую зависит от особенностей грунта и целевого назначения постройки. Среди наиболее популярных вариантов — винтовые сваи, которые отлично подходят для слабых, влажных или болотистых грунтов благодаря простоте установки и минимальному воздействию на почву. Буронабивные сваи, напротив, используют для более твёрдых и плотных оснований: здесь важен продуманный подход к подбору диаметра и глубины бурения, которая обычно варьируется от 3 до 14 метров. Забивные сваи чаще всего применяются в промышленных условиях, где требуется высокая несущая способность и скорость монтажа.</p>\n<p>Современные ямобуры, оснащённые телескопическими стрелами длиной до 12 метров и манипуляторами, существенно облегчают процесс монтажа. Они позволяют не только точно контролировать глубину и вертикальность бурения, но и оперативно поднимать и устанавливать сваи, уменьшая человеческий фактор и риски ошибок. Особенно важен правильный подбор техники для разных видов грунтов — от рыхлых и сыпучих до скальных. В мерзлых или каменистых условиях используют усиленные шнеки и агрегаты с большим тяговым усилием, что повышает производительность и исключает повреждения оборудования.</p>\n\n<h2>Технологии бурения ям под заборы и мелкие конструкции</h2>\n<p>Когда речь идёт о бурении ям для заборов или небольших объектов, задача упрощается, однако сохраняется необходимость точности и аккуратности. Обычно ямы имеют диаметр от 150 до 300 миллиметров и глубину порядка 1,5–2 метров — в зависимости от высоты ограждения, ветровой нагрузки и типа почвы. Для подобных задач идеальны компактные мини-ямобуры, способные эффективно работать даже в ограниченном пространстве — например, в плотной городской застройке или на участках с деревьями и кустарниками.</p>\n<p>Использование телескопических стрел здесь также критично: они обеспечивают доступ в труднодоступные точки, позволяя минимизировать повреждения окружающей среды и избежать лишнего копания. Особое внимание следует уделять выбору шнека и буровой головки с учётом типа грунта: на каменистых или глинистых участках применяются более прочные и износостойкие элементы, способные выдержать нагрузку и ускорить процесс. Кроме того, грамотное планирование параметров бурения позволяет оптимизировать расход материалов и снизить затраты времени.</p>\n\n<h2>ТОП-5 эффективных решений для бурения и монтажа в различных условиях</h2>\n<p>Для успешной реализации буровых работ и монтажа столбов и фундаментов стоит использовать проверенные решения, адаптированные под конкретные задачи и условия:</p>\n<ol>\n<li><strong>Мини-ямобуры для ограниченных пространств:</strong> Эти компактные машины идеальны для узких участков или участков с плотной застройкой — ими легко работать меж деревьев и построек, а благодаря небольшой массе техника не повреждает грунт.</li>\n<li><strong>Манипуляторы для монтажа тяжёлых столбов и опор ЛЭП:</strong> Использование манипуляторов обеспечивает высокую точность установки и безопасность, уменьшая необходимость ручного труда.</li>\n<li><strong>Телескопические стрелы:</strong> Благодаря возможности регулировать длину, они позволяют бурить в сложных и ограниченных условиях, где невозможно использование стационарного оборудования.</li>\n<li><strong>Вездеходная техника для сложных грунтов и рельефа:</strong> В условиях лесных массивов, холмистых или каменистых территорий важна проходимость и устойчивость техники, что обеспечивает спецоборудование с полным приводом и усиленной подвеской.</li>\n<li><strong>Комбинированные буровые и крановые операции:</strong> Часто при монтаже необходимо не только пробурить отверстия, но и сразу установить конструкционные элементы. Совмещение функций сокращает время и расходы.</li>\n</ol>\n\n<h2>Практические кейсы и отзывы заказчиков</h2>\n<p>Опыт работы с реальными клиентами подтверждает эффективность современных подходов. Например, при возведении небольшого дома в Челябинске использовался ямобур на базе Isuzu для бурения свай диаметром 400 мм глубиной до 10 метров. Благодаря слаженной работе оператора и современному оборудованию одна яма бурилась менее чем за минуту. Клиент отметил высокую скорость и точность, что особенно важно в условиях ограниченного бюджета и сжатых сроков.</p>\n<p>Другой случай связан с монтажом забора на сыпучем грунте, где применялись мини-ямобур и телескопическая стрела. Такой подход позволил минимизировать повреждение участка, выполнить работы аккуратно и без лишних затрат. Отзывы подчёркивают: грамотное сочетание техники и квалифицированных специалистов — залог успешного результата. Компания БурЭксперт рекомендует всегда учитывать особенности грунта и специфику объекта при планировании и выборе техники, чтобы избежать ошибок и перерасходов.</p>\n\n<h2>Технические особенности и инновации спецтехники для бурения</h2>\n<p>Современные ямобуры и буровые установки оснащены техническими решениями, которые существенно повышают производительность и надёжность. Телескопические стрелы обеспечивают гибкую настройку длины и позволяют работать в самых разных условиях, от городских кварталов до лесных массивов. Манипуляторы дают возможность с лёгкостью управлять тяжелыми элементами — будь то сваи, опоры ЛЭП или строительные столбы.</p>\n<p>Материалы шнеков и буровых насадок разрабатываются с учётом высокой износостойкости, что позволяет успешно справляться с каменистыми и плотными грунтами без повреждений и простоев. Кроме того, современные энергоэффективные двигатели и гидравлические системы снижают уровень шума и расход топлива, что делает работы экологичнее и экономичнее. Эти инновации обеспечивают не только производительность, но и безопасность — важный аспект на строительных площадках любого масштаба.</p>\n\n<h2>Заключение</h2>\n<p>Выбор правильной технологии бурения и монтажа фундаментов — это ключ к надёжности и долговечности любой конструкции. Современные буровые установки, оборудованные телескопическими стрелами и манипуляторами, позволяют адаптироваться к разным условиям и требованиям проекта, экономя время и средства заказчика. Комплексный подход, включающий профессиональное оборудование, опытных операторов и тщательное планирование, обеспечивает высокое качество работ.</p>\n<p>Компания БурЭксперт рекомендует доверять монтаж фундаментов и бурение ям профессионалам, которые обладают опытом и современным парком техники. Тогда каждый этап строительства будет выполняться максимально эффективно и без сбоев, а результат превзойдёт ожидания.</p>"}