{"id":1,"title":"Аренда ямобуров в Челябинске: полный гид по выбору и выгодным условиям","excerpt":"Узнайте, как правильно выбрать и арендовать ямобур в Челябинске и области. Полная информация о техниках, ценах, ведущих компаниях и практические советы для эффективного бурения под фундамент и другие задачи.","image":"https://example.com/images/chelyabinsk-yamobur-rental-400x300.jpg","date":"2024-06-15","readTime":"7 мин","slug":"arenda-yamoburov-chelyabinsk-polnyy-gid","meta":{"title":"Аренда ямобуров в Челябинске: выгодно и надёжно","description":"Подробный гид по аренде ямобуров в Челябинске — выбор техники, цены, ведущие компании и советы для эффективного бурения. Экономьте время и средства с профессионалами!"},"html":"<h1>Аренда ямобуров в Челябинске: полный гид по выбору и выгодным условиям</h1><h2>Введение</h2><p>Ямобуры — ключевая специализированная техника для бурения глубоких и точных скважин в грунте, которая незаменима при строительстве. В Челябинске и области аренда ямобуров становится всё более популярной услугой как для частных застройщиков, так и для крупных строительных компаний. Это объясняется универсальностью оборудования, его способностью работать в самых разных условиях, а также ощутимой выгодой аренды по сравнению с покупкой собственного агрегата.</p><p>В этой статье мы детально рассмотрим, когда и зачем стоит взять ямобур в аренду, на что обращать внимание при выборе подходящего оборудования, как формируется цена на аренду в регионе, какие компании пользуются заслуженным доверием, а также поделимся экспертными рекомендациями для успешного сотрудничества и максимально эффективного использования техники.</p><h2>1. Что такое ямобур и где он применяется</h2><p>Ямобур — это мощный бурильный агрегат, предназначенный для вертикального бурения грунта с глубиной до 12–14 метров и диаметром скважин от 150 до 900 мм, а порой и до 15 метров глубиной. Такая техника незаменима в строительной отрасли, когда требуется надежное создание отверстий в земле под различные инженерные задачи.</p><p>Основные направления использования ямобуров включают бурение отверстий под фундамент — свайные основания для жилых и промышленных объектов; создание ям под заборы, опоры линий электропередач и другие столбы; установку винтовых свай, ускоряющих строительство прочных фундаментов; бурение колодцев, септиков, дренажных и накопительных ям, что жизненно важно в инженерном обустройстве территории. Особенность ямобуров — возможность работать с разными типами почв, начиная от песка и глины до подверженных сложностям пород вплоть до 5 категории, что обеспечивает универсальность и надежность при любых условиях.</p><h2>2. Преимущества аренды ямобура в Челябинске</h2><p>Аренда ямобура в Челябинске часто выбирается как оптимальный вариант по нескольким ключевым причинам. Во-первых, это значительная экономия, ведь покупка и содержание собственного бурового оборудования требует больших инвестиций — покупка, обслуживание, ремонт, хранение. Аренда освобождает от этих забот, позволяя использовать технику только тогда, когда она действительно нужна.</p><p>Во-вторых, гибкость — можно подобрать ямобур с нужным диаметром, глубиной бурения и подходящим типом шасси, точно под особенности конкретного проекта. Кроме того, многие компании предоставляют услуги профессиональных операторов с опытом, что существенно повышает качество и скорость работ.</p><p>Немаловажно и то, что арендная техника поставляется оперативно, часто с возможностью подачи на объект в течение часа, что критично при срочных задачах. Работа с исправным и проверенным оборудованием снижает риски простоя, делает весь процесс более предсказуемым и организованным.</p><h2>3. Технические характеристики и виды ямобуров</h2><p>Выбор подходящего ямобура напрямую зависит от технических требований — диаметра и глубины бурения, условий площадки и сложности грунта. Диаметры скважин обычно варьируются от 150 до 900 мм, максимальная глубина — до 14 метров, иногда достигает 15 м. Вылет стрелы, определяющий радиус работы, может быть до 15 метров, что обеспечит удобство бурения даже в ограниченных пространствах.</p><p>Шасси ямобуров представлено разными вариантами — популярны модели на базе Isuzu, Mitsubishi, Nissan, а также более мощные на КАМАЗ и ГАЗ. Для сложных грунтов и труднодоступных участков применяются вездеходные варианты и компактные мини-погрузчики с бурильными насадками. Такая разноплановость техники позволяет подбирать агрегат максимально точно под ваши задачи, будь то бурение свай для коттеджа или инженерных колодцев на сложном участке.</p><h2>4. Условия и цены аренды ямобуров в Челябинске</h2><p>Стоимость аренды ямобура зависит от нескольких факторов. В большинстве случаев расчет производится по времени — цена за час варьируется от 1300 до 2000 рублей, в зависимости от модели техники и условий работы. Кроме того, стоимость может рассчитываться по метражу, особенно при учете сложности грунта и диаметра скважин. Цена за метр бурения колеблется от 100 до 1300 рублей.</p><p>Многие компании устанавливают минимальные нормативы: например, минимальный заказ — 1 метр бурения или фиксированная сумма порядка 2000 рублей. При этом дополнительные услуги, включая доставку техники, наличие оператора, использование вездеходной версии или работы в выходные, влияют на итоговую цену.</p><p>Для примера, в Челябинске тарифы у ведущих игроков обычно выглядят так: «ПТО-конструкция» предлагает бурение по 500 рублей за метр глубины, «Спецпарк24» и «СпецТех» предлагают аренду техники от 1300 рублей в час, а «РегионПром» и «ООО БУРАН» — услуги бурения по цене от 200 рублей за метр. Важно помнить, что конечная стоимость зависит от конкретных условий объекта, особенностей грунта и сроков выполнения работ.</p><h2>5. Ключевые игроки рынка услуг по аренде ямобуров в Челябинске и области</h2><p>Рынок аренды ямобуров в Челябинске представлен как крупными компаниями с собственным автопарком, так и небольшими фирмами и частными подрядчиками. Крупные игроки обеспечивают полный спектр услуг — широкий выбор техники, опытных операторов и надежное сопровождение, что особенно важно для комплексных и масштабных проектов.</p><p>Малые фирмы часто предлагают более гибкие условия, оперативный сервис и выгодные скидки, что привлекает клиентов с небольшими объемами работ или нестандартными задачами. Кроме того, несколько региональных компаний расширяют свою географию, предлагая технику для работы и в соседних областях — это удобно для подрядчиков с большим радиусом работы и межрегиональных проектов.</p><h2>6. Рекомендации по выбору и заказу ямобура</h2><p>Чтобы аренда ямобура прошла максимально эффективно, стоит придерживаться нескольких простых, но важных рекомендаций. Начните с оценки ваших потребностей: определите параметры работ — какой тип грунта, требуемый диаметр и глубина бурения, особенности площадки. Это поможет сузить выбор техники до моделей с нужными характеристиками.</p><p>Обращайте внимание на тип шасси и параметры стрелы — они влияют на маневренность и возможности работы в труднодоступных местах. Обязательно сравнивайте цены и подробные условия аренды, уточняйте минимальные заказные объемы и способы оплаты, а также узнавайте о возможности скидок при заказе больших объемов.</p><p>Не менее важно нанять опытного оператора — профессионализм специалиста напрямую отражается на качестве и скорости выполнения работы. Планируйте сроки с запасом, учитывая время доставки и подачи техники, обращая внимание на возможность срочного заказа. И, наконец, изучайте отзывы и репутацию компаний — надежный партнер поможет избежать технических сбоев и срывов графика, что сбережет ваши время и деньги.</p><h2>7. Выводы и перспективы</h2><p>Аренда ямобуров в Челябинске представляет собой современное и удобное решение для буровых работ любого уровня сложности. Широкий выбор техники разной мощности и класса, прозрачные условия аренды и цена, а также профессиональная поддержка оператора позволяют как частным лицам, так и крупным стройкомпаниям оптимизировать процесс и сократить затраты.</p><p>Рынок аренды спецтехники в регионе активно развивается, способствуя обновлению строительной отрасли, упрощая доступ к высококлассному оборудованию и обеспечивая выполнение проектов с высоким качеством и в установленные сроки. Использование арендованного ямобура – это не просто экономия, но и гарантия надежности сооружений и безопасности строительства в целом.</p><h2>Контакты надежных компаний в Челябинске</h2><p><strong>ПТО-конструкция</strong> — тел. +7 (351) XXX-XX-XX, сайт <a href=\"http://www.pto-chel.ru\" target=\"_blank\" rel=\"nofollow noopener noreferrer\">www.pto-chel.ru</a><br/><strong>Спецпарк24</strong> — тел. +7 (351) XXX-XX-XX, сайт <a href=\"http://www.specpark24.ru\" target=\"_blank\" rel=\"nofollow noopener noreferrer\">www.specpark24.ru</a><br/><strong>РегионПром</strong> — тел. +7 (351) XXX-XX-XX, сайт <a href=\"http://www.rp-chel.ru\" target=\"_blank\" rel=\"nofollow noopener noreferrer\">www.rp-chel.ru</a></p><h2>Экспертное мнение</h2><p>Опираясь на многолетний опыт строительных работ, можно с уверенностью сказать, что аренда ямобуров — это не просто способ сократить затраты. Это эффективный инструмент повышения надежности и скорости бурения, особенно при работе на ответственных объектах. Качественное бурение требует современного оборудования и профессионального подхода — от этого напрямую зависит безопасность и долговечность построек. В Челябинске доступен большой выбор техники, и грамотный выбор оборудования помогает минимизировать риски и избежать непредвиденных затрат уже на этапе заливки фундамента.</p><h2>Итог</h2><p>Правильная организация аренды ямобура — ключ к успешной, быстрой и качественной реализации буровых работ в Челябинске и области. Наш подробный обзор поможет сделать осознанный выбор, обеспечив вашу стройку профессиональной техникой с оптимальным соотношением цены и качества.</p><p>Если хотите получить детальную консультацию или уточнить цены, обращайтесь к проверенным компаниям по аренде ямобуров в вашем регионе уже сегодня. Это сэкономит ваше время и средства, а также гарантирует отличное качество и надежность работ!</p><p><strong>Спасибо за внимание!</strong><br/>Если остались вопросы — пишите, всегда рад помочь.</p><p><em>Автор: эксперт по аренде строительной техники и спецоборудования в Челябинске</em></p>"}